smugapi/__init__.py
smugapi/main.py
smugapi/cli/__init__.py
smugapi/cli/main.py
smugapi/handlers/__init__.py
smugapi/handlers/base.py
smugapi/handlers/index.py
smugapi/handlers/stockquotes.py
smugapi/handlers/weatherbit.py
smugapi/lib/__init__.py
smugapi/lib/chartmoji.py
smugapi/lib/json_utils.py
smugapi/lib/sparkline.py
smugapi/lib/web.py
smugapi-0.8.1.dist-info/LICENSE
smugapi-0.8.1.dist-info/METADATA
smugapi-0.8.1.dist-info/WHEEL
smugapi-0.8.1.dist-info/entry_points.txt
smugapi-0.8.1.dist-info/top_level.txt
smugapi-0.8.1.dist-info/RECORD
