Metadata-Version: 2.1
Name: smugapi
Version: 0.8.1
Summary: helpful api endpoints for smug
Home-page: https://github.com/nod/smugapi
License: UNKNOWN
Platform: UNKNOWN
Classifier: License :: OSI Approved :: MIT License
Classifier: Programming Language :: Python :: 3
Requires-Python: >=3.6
Requires-Dist: click
Requires-Dist: pngcanvas
Requires-Dist: requests
Requires-Dist: tornado
Requires-Dist: webpreview
